engbricks
