Metadata-Version: 2.1
Name: engbricks
Version: 1.0.10
Summary: Problem Solver based on formulas
Home-page: https://github.com/FilipeFraqueiro/engbricks
Author: Filipe Fraqueiro
Author-email: fraqueirofilipe@gmail.com
License: MIT
Platform: UNKNOWN
